translitua/__init__.py
translitua/translit.py
translitua-1.2.3.dist-info/DESCRIPTION.rst
translitua-1.2.3.dist-info/METADATA
translitua-1.2.3.dist-info/RECORD
translitua-1.2.3.dist-info/WHEEL
translitua-1.2.3.dist-info/metadata.json
translitua-1.2.3.dist-info/top_level.txt
