Metadata-Version: 2.0
Name: translitua
Version: 1.2.3
Summary: Official transliteration for ukrainian language
Home-page: https://github.com/dchaplinsky/translit-ua
Author: dchaplinsky, enagorny
Author-email: chaplinsky.dmitry@gmail.com, ideviantik@gmail.com
License: MIT
Keywords: ukrainian transliteration
Platform: UNKNOWN
Classifier: Development Status :: 5 - Production/Stable
Classifier: Intended Audience :: Developers
Classifier: License :: OSI Approved :: MIT License
Classifier: Programming Language :: Python :: 2.6
Classifier: Programming Language :: Python :: 2.7
Classifier: Programming Language :: Python :: 3
Classifier: Programming Language :: Python :: Implementation :: PyPy
Classifier: Programming Language :: Python :: 3.3
Classifier: Programming Language :: Python :: 3.4
Classifier: Natural Language :: Ukranian
Classifier: Topic :: Text Processing
